{
    "Action": "AutorunLaunchDaemonFound",
    "EventGUID": "098764f6-9dc1-4451-8812-509023c0b92d",
    "EventID": 269,
    "EventRuleName": "AutorunLaunchDaemonFound - Launch Daemon Info",
    "EventRulesVersion": "202410231648",
    "EventTime": "2024-10-30T10:31:09.731",
    "ServiceVersion": "1.3.0",
    "SystemAgentID": "standalone-run",
    "SystemHostname": "test",
    "SystemMachineSN": "TEST",
    "SystemOSName": "macOS 15.0.1 arm64 #24.0.0",
    "SystemOSType": "darwin",
    "asep_file_ace_mask": "0100644",
    "asep_file_age": 2528420,
    "asep_file_atime": "2024-10-01T04:10:49.000",
    "asep_file_crtime": "2024-10-01T04:10:49.000",
    "asep_file_group_id": 0,
    "asep_file_group_name": "wheel",
    "asep_file_inode": 1152921500312187463,
    "asep_file_mage": 2528420,
    "asep_file_mtime": "2024-10-01T04:10:49.000",
    "asep_file_name": "test.audio.AudioComponentRegisttest.plist",
    "asep_file_nlink": 1,
    "asep_file_owner_id": 0,
    "asep_file_owner_name": "root",
    "asep_file_path": "/System/Library/LaunchDaemons/test.audio.AudioComponentRegisttest.plist",
    "asep_file_size": 669,
    "asep_file_type": "File",
    "asep_type": "LaunchDaemon",
    "cmdline": "/System/Library/Frameworks/AudioTooltest/AudioComponentRegistrar -daemon",
    "cmdline_fingerprint": "67F9DEF989EC835F89463C9CB9852749",
    "customer_id": "local-stand",
    "dev_fqdn": "test",
    "dev_id": "standalone-run",
    "dev_ipv4": "1.1.1.1",
    "dev_os": "macOS 15.0.1 arm64 #24.0.0",
    "dev_os_type": "darwin",
    "dev_serial": "TEST",
    "event_id": 269,
    "event_log_source": "InventoryNG",
    "event_type": "AsepInfo",
    "event_type_vendor": "AutorunLaunchDaemonFound",
    "event_utc_time": "2024-10-30T10:31:09.731",
    "event_uuid": "098764f6-9dc1-4451-8812-509023c0b92d",
    "file_ace_mask": "0100755",
    "file_age": 2528420,
    "file_atime": "2024-10-01T04:10:49.000",
    "file_content": "\\xca\\xfe\\xba\\xbe\\x00\\x00\\x00\\x02\\x01\\x00\\x00\\a\\x00\\x00\\x00\\x03\\x00\\x00@\\x00\\x00\\x00\\x8f\\xd0\\x00\\x00\\x00\\x0e\\x01\\x00\\x00\\f\\x80\\x00\\x00\\x02\\x00\\x01\\x00\\x00\\x00\\x01\\x10\\xd0\\x00\\x00\\x00\\x0e\\x00\\x00",
    "file_crtime": "2024-10-01T04:10:49.000",
    "file_exists": true,
    "file_group_id": 0,
    "file_group_name": "wheel",
    "file_inode": 1152921500312122580,
    "file_mage": 2528420,
    "file_md5": "CB40EDD025A4F929F7E6ACDB6C051EE8",
    "file_mtime": "2024-10-01T04:10:49.000",
    "file_name": "AudioComponentRegistrar",
    "file_nlink": 1,
    "file_owner_id": 0,
    "file_owner_name": "root",
    "file_path": "/System/Library/Frameworks/AudioTooltest/AudioComponentRegistrar",
    "file_sha256": "DA5A145B30D7F47BFA0769E35FC7C8148DFC98004777E766B2C8D3D1001A612F",
    "file_sig": "Software Signing",
    "file_sig_ca": "Apple System",
    "file_sig_cdhash": "8F21A49D7B2BAFCE81D8EDBA9F61928523BDFF13",
    "file_sig_ident": "test.AudioComponentRegistrar",
    "file_sig_result": true,
    "file_sig_status": "Good",
    "file_signed": true,
    "file_size": 135376,
    "file_type": "File",
    "file_yara_matches": 0,
    "file_yara_scope": "File",
    "file_yara_status": 0,
    "inventory_op_type": "Snapshot",
    "inventory_session_id": 17302842690000001,
    "inventory_task_name": "Autoruns - Inventory",
    "rule_name": "AutorunLaunchDaemonFound - Launch Daemon Info",
    "sensor_cfg_profile": "triage",
    "sensor_cfg_profile_id": "60",
    "sensor_cfg_version": "202410231648",
    "sensor_version": "1.3.0"
}