{
  "Action": "AutorunBashEntryFound",
  "EventGUID": "116af103-7774-4ec0-9576-0b7bf0cc193a",
  "EventID": 261,
  "EventRuleName": "AutorunBashEntryFound - Bash Script Entry Info",
  "EventRulesVersion": "202310250055",
  "EventTime": "2023-11-01T10:19:48.729",
  "ServiceVersion": "0.0.10558",
  "SystemAgentID": "standalone-run",
  "SystemHostname": "edr-deb-11",
  "SystemOSName": "Debian GNU/Linux 11 (bullseye) x86_64 #5.10.191-cs4118",
  "SystemOSType": "linux",
  "asep_crtime": "2023-05-29T14:55:59.644",
  "asep_file_ace_mask": "0100644",
  "asep_file_age": 13461829,
  "asep_file_atime": "2023-10-31T14:35:31.103",
  "asep_file_crtime": "2023-05-29T14:55:59.644",
  "asep_file_group_id": 0,
  "asep_file_group_name": "root",
  "asep_file_inode": 784963,
  "asep_file_inode_flags": "--------------e-------",
  "asep_file_mage": 50427558,
  "asep_file_mtime": "2022-03-27T18:40:30.000",
  "asep_file_nlink": 1,
  "asep_file_owner_id": 0,
  "asep_file_owner_name": "root",
  "asep_file_path": "/etc/bash.bashrc",
  "asep_file_size": 1994,
  "asep_file_type": "File",
  "asep_mtime": "2022-03-27T18:40:30.000",
  "asep_type": "BashScript",
  "asep_usr_name": "root",
  "cmdline": "if [ -x /usr/lib/command-not-found -o -x /usr/share/command-not-found/command-not-found ]; then\n\tfunction command_not_found_handle {\n\n\t\tif [ -x /usr/lib/command-not-found ]; then\n\t\t\t/usr/lib/command-not-found -- \"$1\"\n\t\t\treturn $?\n\t\telif [ -x /usr/share/command-not-found/command-not-found ]; then\n\t\t\t/usr/share/command-not-found/command-not-found -- \"$1\"\n\t\t\treturn $?\n\t\telse\n\t\t\tprintf \"%s: command not found\\n\" \"$1\" >&2\n\t\t\treturn 127\n\t\tfi\n\t}\nfi",
  "cmdline_fingerprint": "AD49CA6EABB60D107B76A0549E0B7B9A",
  "dev_fqdn": "edr-deb-11",
  "dev_os": "Debian GNU/Linux 11 (bullseye) x86_64 #5.10.191-cs4118",
  "dev_os_type": "linux",
  "event_id": 261,
  "event_type": "AsepInfo",
  "event_type_vendor": "AutorunBashEntryFound",
  "event_utc_time": "2023-11-01T10:19:48.729",
  "event_uuid": "116af103-7774-4ec0-9576-0b7bf0cc193a",
  "file_app_productname": "NOT FOUND",
  "file_dir": "/usr/share",
  "file_dir_ace_mask": "0040755",
  "file_dir_group_id": 0,
  "file_dir_group_name": "root",
  "file_dir_owner_id": 0,
  "file_dir_owner_name": "root",
  "file_exists": false,
  "file_path": "/usr/share/command-not-found/command-not-found",
  "file_yara_matches": 0,
  "file_yara_status": 0,
  "inventory_op_type": "Snapshot",
  "inventory_session_id": 16988339650000002,
  "inventory_task_name": "Autoruns - Inventory",
  "rule_name": "AutorunBashEntryFound - Bash Script Entry Info",
  "sensor_cfg_profile": "one-shot",
  "sensor_cfg_profile_id": "10",
  "sensor_cfg_version": "202310250055",
  "sensor_version": "0.0.10558"
}
